{
  "version": "5.2.4",
  "background": "#FFFFFF",
  "width": 1080,
  "height": 1500,
  "backgroundImage": {
    "type": "image",
    "version": "5.2.4",
    "originX": "left",
    "originY": "top",
    "left": 0,
    "top": 0,
    "width": 1500,
    "height": 1080,
    "fill": "#1C1C1C",
    "stroke": null,
    "strokeWidth": 0,
    "selectable": false,
    "objectType": "BG",
    "mode": "color",
    "src": "data:image/png;base64,iVBORw0KGgoAAAANSUhEUgAAAAEAAAABCAQAAAC1HAwCAAAAC0lEQVR42mP8/x8AAwMB/6XU4rYAAAAASUVORK5CYII=",
    "filters": []
  },
  "objects": [
    {
      "type": "rect",
      "left": 0,
      "top": 0,
      "width": 1080,
      "height": 1500,
      "fill": "#FFFFFF",
      "objectType": "background"
    },

    {
      "type": "textbox",
      "left": 130,
      "top": 100,
      "width": 800,
      "fill": "#3A3A3A",
      "fontFamily": "Great Vibes",
      "fontWeight": "600",
      "fontSize": 60,
      "text": "Salford Restaurant",
      "textAlign": "left",
      "objectType": "restaurant-name"
    },
    {
      "type": "textbox",
      "left": 120,
      "top": 160,
      "width": 850,
      "fill": "#B1451C",
      "fontFamily": "Montserrat",
      "fontWeight": "900",
      "fontSize": 120,
      "text": "FOOD MENU",
      "textAlign": "left",
      "objectType": "menu-title"
    },

    {
      "type": "circle",
      "left": 980,
      "top": 60,
      "radius": 6,
      "fill": "#000000",
      "objectType": "decor-dot"
    },
    {
      "type": "circle",
      "left": 1000,
      "top": 60,
      "radius": 6,
      "fill": "#000000",
      "objectType": "decor-dot"
    },
    {
      "type": "circle",
      "left": 1020,
      "top": 60,
      "radius": 6,
      "fill": "#000000",
      "objectType": "decor-dot"
    },

    {
      "type": "path",
      "path": [["M", 0, 0], ["Q", 200, 200, 0, 400], ["L", 0, 0]],
      "left": 0,
      "top": 0,
      "fill": "#F3E9DC",
      "objectType": "left-curve"
    },

    {
      "type": "image",
      "left": 120,
      "top": 350,
      "width": 360,
      "height": 470,
      "rx": 25,
      "ry": 25,
      "src": "https://media.istockphoto.com/id/839988946/photo/whats-on-your-pizza.jpg?s=612x612&w=0&k=20&c=5PkXCPJivtGk68sbbTZvypqMOGpxkF-NdbRZzTSFqds=",
      "objectType": "main-image"
    },

    {
      "type": "rect",
      "left": 520,
      "top": 350,
      "width": 500,
      "height": 470,
      "stroke": "#000000",
      "strokeWidth": 2,
      "fill": "#FFFFFF",
      "rx": 25,
      "ry": 25,
      "objectType": "main-course-box"
    },
    {
      "type": "textbox",
      "left": 540,
      "top": 370,
      "width": 270,
      "fill": "#B1451C",
      "fontFamily": "Montserrat",
      "fontWeight": "800",
      "fontSize": 32,
      "text": "MAIN COURSE",
      "textAlign": "left",
      "objectType": "menu-section"
    },
    {
      "type": "textbox",
      "left": 890,
      "top": 370,
      "width": 100,
      "fill": "#B1451C",
      "fontFamily": "Montserrat",
      "fontWeight": "800",
      "fontSize": 32,
      "text": "PRICE",
      "textAlign": "right",
      "objectType": "menu-section"
    },
    {
      "type": "textbox",
      "left": 540,
      "top": 420,
      "width": 300,
      "fill": "#000000",
      "fontFamily": "Poppins",
      "fontSize": 24,
      "text": "Classic Cheeseburger\nGrilled Ribeye Steak\nSpaghetti Carbonara\nChicken Alfredo Pasta\nHalf Rack BBQ Ribs\nMargherita Pizza\nPepperoni Pizza\nClub Sandwich\nGrilled Salmon Fillet\nChicken Quesadilla\nCreamy Mushroom Soup\nFrench Onion Soup",
      "textAlign": "left",
      "objectType": "menu-item"
    },
    {
      "type": "textbox",
      "left": 880,
      "top": 420,
      "width": 120,
      "fill": "#000000",
      "fontFamily": "Poppins",
      "fontSize": 24,
      "text": "$10.99\n$24.50\n$12.00\n$13.00\n$18.00\n$11.00\n$12.00\n$9.50\n$19.00\n$10.50\n$6.00\n$6.50",
      "textAlign": "right",
      "objectType": "price"
    },

    {
      "type": "rect",
      "left": 120,
      "top": 870,
      "width": 900,
      "height": 260,
      "stroke": "#000000",
      "strokeWidth": 2,
      "fill": "#FFFFFF",
      "rx": 25,
      "ry": 25,
      "objectType": "drink-box"
    },
    {
      "type": "textbox",
      "left": 140,
      "top": 890,
      "width": 250,
      "fill": "#B1451C",
      "fontFamily": "Montserrat",
      "fontWeight": "800",
      "fontSize": 32,
      "text": "DRINK MENU",
      "textAlign": "left",
      "objectType": "menu-section"
    },
    {
      "type": "textbox",
      "left": 450,
      "top": 890,
      "width": 100,
      "fill": "#B1451C",
      "fontFamily": "Montserrat",
      "fontWeight": "800",
      "fontSize": 32,
      "text": "PRICE",
      "textAlign": "left",
      "objectType": "menu-section"
    },
    {
      "type": "textbox",
      "left": 140,
      "top": 940,
      "width": 300,
      "fill": "#000000",
      "fontFamily": "Poppins",
      "fontSize": 24,
      "text": "Iced Lemon Tea\nFresh Orange Juice\nCaramel Iced Coffee\nMineral Water",
      "textAlign": "left",
      "objectType": "menu-item"
    },
    {
      "type": "textbox",
      "left": 450,
      "top": 940,
      "width": 100,
      "fill": "#000000",
      "fontFamily": "Poppins",
      "fontSize": 24,
      "text": "$3.50\n$4.50\n$5.00\n$2.00",
      "textAlign": "left",
      "objectType": "price"
    },
    {
      "type": "image",
      "left": 700,
      "top": 890,
      "width": 300,
      "height": 220,
      "rx": 20,
      "ry": 20,
      "src": "https://www.shutterstock.com/image-photo/neapolitan-pizza-spices-tomatoes-cheese-260nw-2272483867.jpg",
      "objectType": "drink-image"
    },

    {
      "type": "rect",
      "left": 120,
      "top": 1200,
      "width": 250,
      "height": 70,
      "fill": "#B1451C",
      "rx": 35,
      "ry": 35,
      "objectType": "reservation-btn-bg"
    },
    {
      "type": "textbox",
      "left": 140,
      "top": 1220,
      "width": 200,
      "fill": "#FFFFFF",
      "fontFamily": "Montserrat",
      "fontWeight": "700",
      "fontSize": 26,
      "text": "RESERVATION",
      "textAlign": "center",
      "objectType": "reservation-btn-text"
    },
    {
      "type": "circle",
      "left": 430,
      "top": 1210,
      "radius": 22,
      "fill": "#B1451C",
      "objectType": "web-icon-bg"
    },
    {
      "type": "textbox",
      "left": 433,
      "top": 1215,
      "width": 500,
      "fill": "#000000",
      "fontFamily": "Montserrat",
      "fontSize": 30,
      "text": "🌐",
      "textAlign": "left",
      "objectType": "footer-text"
    },
    {
      "type": "textbox",
      "left": 480,
      "top": 1205,
      "width": 500,
      "fill": "#000000",
      "fontFamily": "Montserrat",
      "fontSize": 22,
      "text": "Visit Our Website\nwww.reallygreatsite.com",
      "textAlign": "left",
      "objectType": "footer-text"
    }
  ]
}
